kkf/DynamicalSystems.py
kkf/KKFsol.py
kkf/__init__.py
kkf/applyKKF.py
kkf/covariances.py
kkf/kEDMD.py
kkf/utils.py
kkf-0.23.dist-info/LICENSE
kkf-0.23.dist-info/METADATA
kkf-0.23.dist-info/WHEEL
kkf-0.23.dist-info/top_level.txt
kkf-0.23.dist-info/RECORD
