Metadata-Version: 2.1
Name: kkf
Version: 0.23
Summary: kkf: a library for Python implementation of Kernel-Koopman-Kalman Filter.
Home-page: https://github.com/diegoolguinw/kkf
Author: Diego Olguin-Wende
Author-email: dolguin@dim.uchile.cl
Classifier: Programming Language :: Python :: 3
Classifier: License :: OSI Approved :: MIT License
Classifier: Operating System :: OS Independent
Requires-Python: >=3.6
License-File: LICENSE
Requires-Dist: numpy
Requires-Dist: scipy
Requires-Dist: scikit-learn
